junos_eznc-2.7.4-py3.9-nspkg.pth
jnpr/junos/__init__.py
jnpr/junos/_version.py
jnpr/junos/console.py
jnpr/junos/decorators.py
jnpr/junos/device.py
jnpr/junos/exception.py
jnpr/junos/factcache.py
jnpr/junos/jxml.py
jnpr/junos/rpcmeta.py
jnpr/junos/version.py
jnpr/junos/cfg/__init__.py
jnpr/junos/cfg/resource.py
jnpr/junos/cfg/user.py
jnpr/junos/cfg/user_ssh_key.py
jnpr/junos/cfg/phyport/__init__.py
jnpr/junos/cfg/phyport/base.py
jnpr/junos/cfg/phyport/classic.py
jnpr/junos/cfg/phyport/switch.py
jnpr/junos/cfgro/__init__.py
jnpr/junos/cfgro/srx.yml
jnpr/junos/command/__init__.py
jnpr/junos/command/chassis_fan.yml
jnpr/junos/command/cm_error.yml
jnpr/junos/command/ea_drd_error.yml
jnpr/junos/command/ea_fi_error.yml
jnpr/junos/command/ea_fi_statistics.yml
jnpr/junos/command/ea_fo_statistics.yml
jnpr/junos/command/ea_host_drop.yml
jnpr/junos/command/ea_li_error.yml
jnpr/junos/command/ea_lo_statistics.yml
jnpr/junos/command/ea_pt_statistics.yml
jnpr/junos/command/ea_wi_statistics.yml
jnpr/junos/command/ea_wo_statistics.yml
jnpr/junos/command/fpc_link_stats.yml
jnpr/junos/command/fpc_memory.yml
jnpr/junos/command/fpc_threads.yml
jnpr/junos/command/host_loopback_status.yml
jnpr/junos/command/ithrottle.yml
jnpr/junos/command/jnh_exceptions.yml
jnpr/junos/command/jnh_ifd_stream.yml
jnpr/junos/command/jnhexceptionpkt.yml
jnpr/junos/command/linecard_ethernet_statistics.yml
jnpr/junos/command/ospf_neighbor.yml
jnpr/junos/command/pci_error.yml
jnpr/junos/command/pfe_ddos_policer.yml
jnpr/junos/command/pre_classifier.yml
jnpr/junos/command/scheduler_info.yml
jnpr/junos/command/system_proc_ext.yml
jnpr/junos/command/system_queues.yml
jnpr/junos/command/task_io.yml
jnpr/junos/command/toe_pfe.yml
jnpr/junos/command/veriexec.yml
jnpr/junos/command/vmcores.yml
jnpr/junos/command/xm_drd_error.yml
jnpr/junos/command/xm_fi_error.yml
jnpr/junos/command/xm_fi_statistics.yml
jnpr/junos/command/xm_fo_statistics.yml
jnpr/junos/command/xm_host_drop.yml
jnpr/junos/command/xm_li_error.yml
junos_eznc-2.7.4.dist-info/LICENSE
junos_eznc-2.7.4.dist-info/METADATA
junos_eznc-2.7.4.dist-info/WHEEL
junos_eznc-2.7.4.dist-info/namespace_packages.txt
junos_eznc-2.7.4.dist-info/top_level.txt
junos_eznc-2.7.4.dist-info/RECORD
